lcapy/__init__.py
lcapy/abc.py
lcapy/acdc.py
lcapy/admittance.py
lcapy/admittancemixin.py
lcapy/admittancesquaredmixin.py
lcapy/analysis.py
lcapy/approximate.py
lcapy/assumptions.py
lcapy/attrdict.py
lcapy/cache.py
lcapy/capacitance.py
lcapy/cexpr.py
lcapy/circuit.py
lcapy/circuitgraph.py
lcapy/classmap.py
lcapy/cnodes.py
lcapy/componentnamer.py
lcapy/components.py
lcapy/conductance.py
lcapy/config.py
lcapy/context.py
lcapy/current.py
lcapy/currentmixin.py
lcapy/currentsquaredmixin.py
lcapy/deprecation.py
lcapy/dexpr.py
lcapy/dft.py
lcapy/differenceequation.py
lcapy/differentialequation.py
lcapy/discretetime.py
lcapy/dltifilter.py
lcapy/domains.py
lcapy/dtft.py
lcapy/dtstatespace.py
lcapy/equation.py
lcapy/equipotentialnodes.py
lcapy/expr.py
lcapy/exprclasses.py
lcapy/exprdomain.py
lcapy/exprmap.py
lcapy/extrafunctions.py
lcapy/fexpr.py
lcapy/fitter.py
lcapy/fourier.py
lcapy/functions.py
lcapy/grammar.py
lcapy/hilbert.py
lcapy/immittancemixin.py
lcapy/impedance.py
lcapy/impedancemixin.py
lcapy/impedancesquaredmixin.py
lcapy/inductance.py
lcapy/inverse_dft.py
lcapy/inverse_dtft.py
lcapy/inverse_fourier.py
lcapy/inverse_hilbert.py
lcapy/inverse_laplace.py
lcapy/inverse_ztransform.py
lcapy/jfexpr.py
lcapy/jomegaexpr.py
lcapy/kexpr.py
lcapy/kseq.py
lcapy/label.py
lcapy/labelmaker.py
lcapy/labels.py
lcapy/laddermaker.py
lcapy/laddernetworkmaker.py
lcapy/laplace.py
lcapy/latex.py
lcapy/loopanalysis.py
lcapy/ltifilter.py
lcapy/makeclasses.py
lcapy/matrix.py
lcapy/mna.py
lcapy/mnacpts.py
lcapy/netfile.py
lcapy/netlist.py
lcapy/netlisthelper.py
lcapy/netlistmaker.py
lcapy/netlistmixin.py
lcapy/netlistnamespace.py
lcapy/netlistopsmixin.py
lcapy/netlistsimplifymixin.py
lcapy/nettransform.py
lcapy/network.py
lcapy/nexpr.py
lcapy/nmatrix.py
lcapy/nodalanalysis.py
lcapy/node.py
lcapy/nodes.py
lcapy/noiseexpr.py
lcapy/noisefexpr.py
lcapy/noiseomegaexpr.py
lcapy/normfexpr.py
lcapy/normomegaexpr.py
lcapy/nseq.py
lcapy/omegaexpr.py
lcapy/oneport.py
lcapy/opts.py
lcapy/parser.py
lcapy-1.26.dist-info/LICENCE
lcapy-1.26.dist-info/METADATA
lcapy-1.26.dist-info/WHEEL
lcapy-1.26.dist-info/entry_points.txt
lcapy-1.26.dist-info/top_level.txt
lcapy-1.26.dist-info/RECORD
