Metadata-Version: 2.1
Name: lcapy
Version: 1.26
Summary: Symbolic linear circuit analysis
Home-page: https://github.com/mph-/lcapy
Author: Michael Hayes
Author-email: michael.hayes@canterbury.ac.nz
License: UNKNOWN
Download-URL: https://github.com/mph-/lcapy
Platform: UNKNOWN
Classifier: Programming Language :: Python :: 3
Classifier: License :: OSI Approved :: GNU Lesser General Public License v2 or later (LGPLv2+)
Classifier: Operating System :: OS Independent
Requires-Python: >=3.7
Requires-Dist: IPython
Requires-Dist: importlib
Requires-Dist: matplotlib
Requires-Dist: networkx
Requires-Dist: numpy
Requires-Dist: packaging
Requires-Dist: property-cached
Requires-Dist: scipy
Requires-Dist: setuptools
Requires-Dist: sympy (>=1.10.1)
Requires-Dist: wheel
Provides-Extra: doc
Requires-Dist: docutils ; extra == 'doc'
Requires-Dist: ipython ; extra == 'doc'
Requires-Dist: pygments ; extra == 'doc'
Requires-Dist: sphinx-rtd-theme ; extra == 'doc'
Requires-Dist: sphinx (>=7) ; extra == 'doc'
Provides-Extra: release
Requires-Dist: twine ; extra == 'release'
Requires-Dist: wheel ; extra == 'release'
Provides-Extra: test
Requires-Dist: flake8 ; extra == 'test'
Requires-Dist: flake8-bugbear ; extra == 'test'
Requires-Dist: flake8-comprehensions ; extra == 'test'
Requires-Dist: flake8-requirements ; extra == 'test'
Requires-Dist: pytest ; extra == 'test'
